ephysworking/__init__.py
ephysworking/utils.py
ephysworking/inter_session_alignment/README.md
ephysworking/inter_session_alignment/__init__.py
ephysworking/inter_session_alignment/save_data_plots.py
ephysworking/inter_session_alignment/scripts/README.md
ephysworking/inter_session_alignment/scripts/motion_correction_pipeline.py
ephysworking/inter_session_alignment/scripts/preprocess_session.py
ephysworking/inter_session_alignment/utils/calculate_histogram_shift.py
ephysworking/inter_session_alignment/utils/histogram_generation.py
ephysworking/inter_session_alignment/utils/pipeline_steps.py
ephysworking/motion_correction_compare/__init__.py
ephysworking/motion_correction_compare/motion_utils.py
ephysworking/motion_correction_compare/scripts/dammy_mre.py
ephysworking/motion_correction_compare/scripts/run_si_and_ks_motion_correction.py
ephysworking-0.0.2.dist-info/LICENSE
ephysworking-0.0.2.dist-info/METADATA
ephysworking-0.0.2.dist-info/WHEEL
ephysworking-0.0.2.dist-info/top_level.txt
ephysworking-0.0.2.dist-info/RECORD
